[
    {
        "name": "Axe",
        "species": ["Orc"],
        "sortSpecies": "Orc",
        "sortClass": "Warrior",
        "class": ["Warrior"],
        "cost": 1
    },
    {
        "name": "Enchantress",
        "species": ["Beast"],
        "sortSpecies": "Beast",
        "sortClass": "Druid",
        "class": ["Druid"],
        "cost": 1
    },
    {
        "name": "Ogre Magi",
        "species": ["Ogre"],
        "sortSpecies": "Ogre",
        "sortClass": "Mage",
        "class": ["Mage"],
        "cost": 1
    },
    {
        "name": "Tusk",
        "species": ["Beast"],
        "sortSpecies": "Beast",
        "sortClass": "Warrior",
        "class": ["Warrior"],
        "cost": 1
    },
    {
        "name": "Drow Ranger",
        "species": ["Undead"],
        "sortSpecies": "Undead",
        "sortClass": "Hunter",
        "class": ["Hunter"],
        "cost": 1
    },
    {
        "name": "Bounty Hunter",
        "species": ["Goblin"],
        "sortSpecies": "Goblin",
        "sortClass": "Assassin",
        "class": ["Assassin"],
        "cost": 1
    },
    {
        "name": "Clockwerk",
        "species": ["Goblin"],
        "sortSpecies": "Goblin",
        "sortClass": "Mech",
        "class": ["Mech"],
        "cost": 1
    },
    {
        "name": "Shadow Shaman",
        "species": ["Troll"],
        "sortSpecies": "Troll",
        "sortClass": "Shaman",
        "class": ["Shaman"],
        "cost": 1
    },
    {
        "name": "Bat Rider",
        "species": ["Troll"],
        "sortSpecies": "Troll",
        "sortClass": "Knight",
        "class": ["Knight"],
        "cost": 1
    },
    {
        "name": "Tinker",
        "species": ["Goblin"],
        "sortSpecies": "Goblin",
        "sortClass": "Mech",
        "class": ["Mech"],
        "cost": 1
    },
    {
        "name": "Anti Mage",
        "species": ["Elf"],
        "sortSpecies": "Elf",
        "sortClass": "Hunter",
        "class": ["Demon Hunter"],
        "cost": 1
    },
    {
        "name": "Tiny",
        "species": ["Element"],
        "sortSpecies": "Element",
        "sortClass": "Warrior",
        "class": ["Warrior"],
        "cost": 1
    },
    {
        "name": "Crystal Maiden",
        "species": ["Human"],
        "sortSpecies": "Human",
        "sortClass": "Mage",
        "class": ["Mage"],
        "cost": 2
    },
    {
        "name": "Beast Master",
        "species": ["Orc"],
        "sortSpecies": "Orc",
        "sortClass": "Hunter",
        "class": ["Hunter"],
        "cost": 2
    },
    {
        "name": "Juggernaut",
        "species": ["Orc"],
        "sortSpecies": "Orc",
        "sortClass": "Warrior",
        "class": ["Warrior"],
        "cost": 2
    },
    {
        "name": "Timbersaw",
        "species": ["Goblin"],
        "sortSpecies": "Goblin",
        "sortClass": "Mech",
        "class": ["Mech"],
        "cost": 2
    },
    {
        "name": "Queen of Pain",
        "species": ["Demon"],
        "sortSpecies": "Demon",
        "sortClass": "Assassin",
        "class": ["Assassin"],
        "cost": 2
    },
    {
        "name": "Puck",
        "species": ["Elf","Dragon"],
        "sortSpecies": "Dragon",
        "sortClass": "Mage",
        "class": ["Mage"],
        "cost": 2
    },
    {
        "name": "Witch Doctor",
        "species": ["Troll"],
        "sortSpecies": "Troll",
        "sortClass": "Warlock",
        "class": ["Warlock"],
        "cost": 2
    },
    {
        "name": "Slardar",
        "species": ["Naga"],
        "sortSpecies": "Naga",
        "sortClass": "Warrior",
        "class": ["Warrior"],
        "cost": 2
    },
    {
        "name": "Chaos Knight",
        "species": ["Demon"],
        "sortSpecies": "Demon",
        "sortClass": "Knight",
        "class": ["Knight"],
        "cost": 2
    },
    {
        "name": "Treant Protector",
        "species": ["Elf"],
        "sortSpecies": "Elf",
        "sortClass": "Druid",
        "class": ["Druid"],
        "cost": 2
    },
    {
        "name": "Morphling",
        "species": ["Element"],
        "sortSpecies": "Element",
        "sortClass": "Assassin",
        "class": ["Assassin"],
        "cost": 2
    },
    {
        "name": "Luna",
        "species": ["Elf"],
        "sortSpecies": "Elf",
        "sortClass": "Knight",
        "class": ["Knight"],
        "cost": 2
    },
    {
        "name": "Furion",
        "species": ["Elf"],
        "sortSpecies": "Elf",
        "sortClass": "Druid",
        "class": ["Druid"],
        "cost": 2
    },
    {
        "name": "Lycan",
        "species": ["Human","Beast"],
        "sortSpecies": "Beast",
        "sortClass": "Warrior",
        "class": ["Warrior"],
        "cost": 3
    },
    {
        "name": "Venomancer",
        "species": ["Beast"],
        "sortSpecies": "Beast",
        "sortClass": "Warlock",
        "class": ["Warlock"],
        "cost": 3
    },
    {
        "name": "Omni Knight",
        "species": ["Human"],
        "sortSpecies": "Human",
        "sortClass": "Knight",
        "class": ["Knight"],
        "cost": 3
    },
    {
        "name": "Razor",
        "species": ["Element"],
        "sortSpecies": "Element",
        "sortClass": "Mage",
        "class": ["Mage"],
        "cost": 3
    },
    {
        "name": "Wind Ranger",
        "species": ["Elf"],
        "sortSpecies": "Elf",
        "sortClass": "Hunter",
        "class": ["Hunter"],
        "cost": 3
    },
    {
        "name": "Phantom Assassin",
        "species": ["Elf"],
        "sortSpecies": "Elf",
        "sortClass": "Assassin",
        "class": ["Assassin"],
        "cost": 3
    },
    {
        "name": "Abaddon",
        "species": ["Undead"],
        "sortSpecies": "Undead",
        "sortClass": "Knight",
        "class": ["Knight"],
        "cost": 3
    },
    {
        "name": "Sand King",
        "species": ["Beast"],
        "sortSpecies": "Beast",
        "sortClass": "Assassin",
        "class": ["Assassin"],
        "cost": 3
    },
    {
        "name": "Slark",
        "species": ["Naga"],
        "sortSpecies": "Naga",
        "sortClass": "Assassin",
        "class": ["Assassin"],
        "cost": 3
    },
    {
        "name": "Sniper",
        "species": ["Dwarf"],
        "sortSpecies": "Dwarf",
        "sortClass": "Hunter",
        "class": ["Hunter"],
        "cost": 3
    },
    {
        "name": "Terrorblade",
        "species": ["Demon"],
        "sortSpecies": "Demon",
        "sortClass": "Hunter",
        "class": ["Demon Hunter"],
        "cost": 3
    },
    {
        "name": "Viper",
        "species": ["Dragon"],
        "sortSpecies": "Dragon",
        "sortClass": "Assassin",
        "class": ["Assassin"],
        "cost": 3
    },
    {
        "name": "Shadow Fiend",
        "species": ["Demon"],
        "sortSpecies": "Demon",
        "sortClass": "Warlock",
        "class": ["Warlock"],
        "cost": 3
    },
    {
        "name": "Lina",
        "species": ["Human"],
        "sortSpecies": "Human",
        "sortClass": "Mage",
        "class": ["Mage"],
        "cost": 3
    },
    {
        "name": "Doom",
        "species": ["Demon"],
        "sortSpecies": "Demon",
        "sortClass": "Warrior",
        "class": ["Warrior"],
        "cost": 4
    },
    {
        "name": "Kunkka",
        "species": ["Human"],
        "sortSpecies": "Human",
        "sortClass": "Warrior",
        "class": ["Warrior"],
        "cost": 4
    },
    {
        "name": "Troll Warlord",
        "species": ["Troll"],
        "sortSpecies": "Troll",
        "sortClass": "Warrior",
        "class": ["Warrior"],
        "cost": 4
    },
    {
        "name": "Keeper of the Light",
        "species": ["Human"],
        "sortSpecies": "Human",
        "sortClass": "Mage",
        "class": ["Mage"],
        "cost": 4
    },
    {
        "name": "Necrophos",
        "species": ["Undead"],
        "sortSpecies": "Undead",
        "sortClass": "Warlock",
        "class": ["Warlock"],
        "cost": 4
    },
    {
        "name": "Templar Assassin",
        "species": ["Elf"],
        "sortSpecies": "Elf",
        "sortClass": "Assassin",
        "class": ["Assassin"],
        "cost": 4
    },
    {
        "name": "Alchemist",
        "species": ["Goblin"],
        "sortSpecies": "Goblin",
        "sortClass": "Warlock",
        "class": ["Warlock"],
        "cost": 4
    },
    {
        "name": "Disruptor",
        "species": ["Orc"],
        "sortSpecies": "Orc",
        "sortClass": "Shaman",
        "class": ["Shaman"],
        "cost": 4
    },
    {
        "name": "Medusa",
        "species": ["Naga"],
        "sortSpecies": "Naga",
        "sortClass": "Hunter",
        "class": ["Hunter"],
        "cost": 4
    },
    {
        "name": "Dragon Knight",
        "species": ["Dragon", "Human"],
        "sortSpecies": "Human",
        "sortClass": "Knight",
        "class": ["Knight"],
        "cost": 4
    },
    {
        "name": "Lone Druid",
        "species": ["Beast"],
        "sortSpecies": "Beast",
        "sortClass": "Druid",
        "class": ["Druid"],
        "cost": 4
    },
    {
        "name": "Gyrocopter",
        "species": ["Dwarf"],
        "sortSpecies": "Dwarf",
        "sortClass": "Mech",
        "class": ["Mech"],
        "cost": 5
    },
    {
        "name": "Lich",
        "species": ["Undead"],
        "sortSpecies": "Undead",
        "sortClass": "Mage",
        "class": ["Mage"],
        "cost": 5
    },
    {
        "name": "Tide Hunter",
        "species": ["Naga"],
        "sortSpecies": "Naga",
        "sortClass": "Hunter",
        "class": ["Hunter"],
        "cost": 5
    },
    {
        "name": "Enigma",
        "species": ["Element"],
        "sortSpecies": "Element",
        "sortClass": "Warlock",
        "class": ["Warlock"],
        "cost": 5
    },
    {
        "name": "Techies",
        "species": ["Goblin"],
        "sortSpecies": "Goblin",
        "sortClass": "Mech",
        "class": ["Mech"],
        "cost": 5
    }
]